<?xml version="1.0" encoding="ISO-8859-1" ?>
<EnvioDTE xmlns="http://www.sii.cl/SiiDte" xmlns:xsi="http://www.w3.org/2001/XMLSchema-instance" xsi:schemaLocation="http://www.sii.cl/SiiDte EnvioDTE_v10.xsd" version="1.0">
    <SetDTE ID="SetDoc">
        <Caratula version="1.0">
            <RutEmisor>76276027-4</RutEmisor>
            <RutEnvia>9669996-4</RutEnvia>
            <RutReceptor>60803000-K</RutReceptor>
            <FchResol>2014-08-22</FchResol>
            <NroResol>80</NroResol>
            <TmstFirmaEnv>2025-02-06T10:48:51</TmstFirmaEnv>
            <SubTotDTE>
                <TpoDTE>33</TpoDTE>
                <NroDTE>1</NroDTE>
            </SubTotDTE>
        </Caratula>
        <DTE xmlns="http://www.sii.cl/SiiDte" version="1.0">
            <Documento ID="F12738T33">
            <Encabezado>
                <IdDoc>
                    <TipoDTE>33</TipoDTE>
                    <Folio>12738</Folio>
                    <FchEmis>2025-02-06</FchEmis>
                    <FmaPago>2</FmaPago>
                    <FchVenc>2025-03-08</FchVenc>
                </IdDoc>
                <Emisor>
                    <RUTEmisor>76276027-4</RUTEmisor>
                    <RznSoc>Soc. ADAPTOR Chile SPA</RznSoc>
                    <GiroEmis>Articulos y Servicios de Comunicaciones y Colaboración</GiroEmis>
                    <Telefono>+56 2 2810 6000</Telefono>
                    <CorreoEmisor>facturacion@adaptor.cl</CorreoEmisor>
                    <Acteco>474100</Acteco>
                    <Acteco>619090</Acteco>
                    <DirOrigen>Roger de Flor 2907, local 4 </DirOrigen>
                    <CmnaOrigen>Las Condes</CmnaOrigen>
                    <CdgVendedor>Angélica Ruiz</CdgVendedor>
                </Emisor>
                <Receptor>
                    <RUTRecep>78331790-7</RUTRecep>
                    <RznSocRecep>MADERAS MARTÍN LIMITADA</RznSocRecep>
                    <GiroRecep>INDUSTRIA DE LA MADERA ASERRADO Y ACEPIL</GiroRecep>
                    <Contacto>71671523</Contacto>
                    <CorreoRecep>adquisiciones@maderam.cl</CorreoRecep>
                    <DirRecep>CAMINO SAN JAVIER KM 7                                                </DirRecep>
            <CmnaRecep>Constitución</CmnaRecep>
                </Receptor>
                <Totales>
                    <MntNeto>192488</MntNeto>
                    <TasaIVA>19.00</TasaIVA>
            <IVA>36573</IVA>
                    <MntTotal>229061</MntTotal>
                </Totales>
                <OtraMoneda>
                    <TpoMoneda>OTRAS MONEDAS</TpoMoneda>
                    <TpoCambio>987.12</TpoCambio>
                    <MntNetoOtrMnda>195.00</MntNetoOtrMnda>
                    <IVAOtrMnda>37.05</IVAOtrMnda>
                    <MntTotOtrMnda>232.05</MntTotOtrMnda>
                </OtraMoneda>
            </Encabezado>
            <Detalle>
                <NroLinDet>1</NroLinDet>
                <CdgItem>
                    <TpoCodigo>INT1</TpoCodigo>
                    <VlrCodigo>POL-MICXPN_STUDIO_00</VlrCodigo>
                </CdgItem>
                <NmbItem>Micr.Poly Expansión p/Studio</NmbItem>
                <DscItem>[POL-MICXPN_STUDIO_00] Micr.Poly Expansión p/Studio</DscItem>
                <QtyItem>1.000000</QtyItem>
                <UnmdItem>U</UnmdItem>
                <PrcItem>192488.000000</PrcItem>
                <OtrMnda>
                    <PrcOtrMon>195.00</PrcOtrMon>
                    <Moneda>US*</Moneda>
                    <FctConv>987.1192</FctConv>
                    <MontoItemOtrMnda>195.00</MontoItemOtrMnda>
                </OtrMnda>
                <MontoItem>192488</MontoItem>
            </Detalle>
            <Referencia>
                <NroLinRef>1</NroLinRef>
                <TpoDocRef>801</TpoDocRef>
                <FolioRef>68685</FolioRef>
                <FchRef>2025-02-04</FchRef>
            </Referencia>
            <Referencia>
                <NroLinRef>2</NroLinRef>
                <TpoDocRef>52</TpoDocRef>
                <FolioRef>9740</FolioRef>
                <FchRef>2025-02-06</FchRef>
            </Referencia>
            <TED version="1.0">
            <DD>
                <RE>76276027-4</RE>
                <TD>33</TD>
                <F>12738</F>
                <FE>2025-02-06</FE>
                <RR>78331790-7</RR>
                <RSR>MADERAS MARTÍN LIMITADA</RSR>
                <MNT>229061</MNT>
                <IT1>Micr.Poly Expansión p/Studio</IT1>
                <CAF version="1.0">
                    <DA>
                        <RE>76276027-4</RE>
                        <RS>SOCIEDAD ADAPTOR CHILE SPA</RS>
                        <TD>33</TD>
                        <RNG>
                            <D>12675</D>
                            <H>12774</H>
                        </RNG>
                        <FA>2024-12-30</FA>
                        <RSAPK>
                            <M>/P7sRuvxzA4uC2H2FJdrx6QqlhHLUopW+BzfDZqK4plwYcjEhf9LxxWIFGBht6sxkRBQGyB2nhjLypbH6I3v6w==</M>
                            <E>Aw==</E>
                        </RSAPK>
                        <IDK>300</IDK>
                    </DA>
                    <FRMA algoritmo="SHA1withRSA">UZu1mdWgXwerh1Kb+/miKkg6IyVAcFptBcy2GzpRYhpRe4j2TWb7hv2/3KX7LfrS6aV6kwpAnleIwR8rtajcyg==</FRMA>
                </CAF>
                <TSTED>2025-02-06T10:48:50</TSTED>
            </DD>
                <FRMT algoritmo="SHA1withRSA">uI20EZTKJfyGKWYXvsef+eRIGmZiBkm9LZx09A2x6eeOWLTF+sVsWZLf+ruvjThdvynPlkCEsB5b5rg7zPU2Nw==</FRMT>
            </TED><TmstFirma>2025-02-06T10:48:50</TmstFirma>
            </Documento>
<Signature xmlns="http://www.w3.org/2000/09/xmldsig#"><SignedInfo xmlns="http://www.w3.org/2000/09/xmldsig#"><CanonicalizationMethod Algorithm="http://www.w3.org/TR/2001/REC-xml-c14n-20010315"></CanonicalizationMethod><SignatureMethod Algorithm="http://www.w3.org/2000/09/xmldsig#rsa-sha1"></SignatureMethod><Reference URI="#F12738T33"><Transforms><Transform Algorithm="http://www.w3.org/TR/2001/REC-xml-c14n-20010315"></Transform></Transforms><DigestMethod Algorithm="http://www.w3.org/2000/09/xmldsig#sha1"></DigestMethod><DigestValue>F7rGNt3KITypsK1JtyqvgmEVKn4=</DigestValue></Reference></SignedInfo><SignatureValue>vcf0P4xDwVvnwiEEQtQ8gRUZjv7dM/u7V8L4vaSriQSH00RCEl4jqyKgFh5SGi1jH2q8LlfkQF9wGolDLfrt1WbPeU3vnvFZiPAtYr5G0SZytROq/ghITul+t6+LQhXqmqM1k0z+WKicI49Gwlvrh9WnuqqG3bxkd4Eu8DwHku2jXT7dl11qZvjHgf3QRHorIyGI3Ia1uoyw8JcgvWJPq2/9TRBu5I9Cr1lWJTmJBX5oPxbB9MZt57qG7OokNP75oCbdQBYK1AzHr65o6eWIqQ+xEUvLyC7TaxUU+cBAVlnB1AMMzsXQTS0feo6k/j5hMJqch6Dngzns0dRaz7gkcw==</SignatureValue><KeyInfo><KeyValue><RSAKeyValue><Modulus>zB803gl7VOefQ+HBWUfQ8yxV0rd+wPI/PSSUXNxk8OrhoulkxGA2t0EJXMdl1WjBuOHiDqI0ba4xRZ2BPBq0h3+he4O3wMBegfdTUsQ60l0VzGI3QxaeVfroU81gDZU+LI5m5Y8HgNnije2Oggn7dWB56Jidw5ybwTNT5/28fben2ot4RDcgJYRdTZO/T2Is5A3imjiqPRXRFFzhuiB2GxyKN3ABzu5+kwfZIXtzbrJzm3pZ1SAHtgHo+nf4sA0sAZ+rP55jGt8xOcNlVs5epLfleC1gyHna4j0sNQDEm2sc8rzWm4nqCHfB1yXlke4THH1urzUZ7DhTDui+qZIR+Q==</Modulus><Exponent>AQAB</Exponent></RSAKeyValue></KeyValue><X509Data><X509Certificate>
MIIF6jCCBNKgAwIBAgIICDFeKOa8KIIwDQYJKoZIhvcNAQELBQAwgboxHjAcBgkq
hkiG9w0BCQEWD3NvcG9ydGVAaWRvay5jbDEiMCAGA1UEAwwZSURPSyBGSVJNQSBF
TEVDVFJPTklDQSBWNDEXMBUGA1UECwwOUlVULTc2NjEwNzE4LTQxIDAeBgNVBAsM
F0F1dG9yaWRhZCBDZXJ0aWZpY2Fkb3JhMRkwFwYDVQQKDBBCUE8gQWR2aXNvcnMg
U3BBMREwDwYDVQQHDAhTYW50aWFnbzELMAkGA1UEBhMCQ0wwHhcNMjQxMjA2MTgy
NzU4WhcNMjUxMjA2MTgyNzU4WjB/MScwJQYDVQQDDB5TQU5EUkEgIEtBVElBIENB
TFZPIEJVU1RBTUFOVEUxJjAkBgkqhkiG9w0BCQEWF2NvbnRhYmlsaWRhZEBhZGFw
dG9yLmNsMRIwEAYDVQQFEwk5NjY5OTk2LTQxCzAJBgNVBAYTAkNMMQswCQYDVQQH
DAJSTTCCASIwDQYJKoZIhvcNAQEBBQADggEPADCCAQoCggEBAMwfNN4Je1Tnn0Ph
wVlH0PMsVdK3fsDyPz0klFzcZPDq4aLpZMRgNrdBCVzHZdVowbjh4g6iNG2uMUWd
gTwatId/oXuDt8DAXoH3U1LEOtJdFcxiN0MWnlX66FPNYA2VPiyOZuWPB4DZ4o3t
joIJ+3VgeeiYncOcm8EzU+f9vH23p9qLeEQ3ICWEXU2Tv09iLOQN4po4qj0V0RRc
4bogdhscijdwAc7ufpMH2SF7c26yc5t6WdUgB7YB6Pp3+LANLAGfqz+eYxrfMTnD
ZVbOXqS35XgtYMh52uI9LDUAxJtrHPK81puJ6gh3wdcl5ZHuExx9bq81Gew4Uw7o
vqmSEfkCAwEAAaOCAiwwggIoMAkGA1UdEwQCMAAwHwYDVR0jBBgwFoAUu91K238Q
N4h0Z0WyyrkShODGeBYwgZgGA1UdIASBkDCBjTCBigYKKwYBBAGDjB4BBDB8MCwG
CCsGAQUFBwIBFiBodHRwczovL3BzYy5pZG9rLmNsL29wZW4vY3BzLnBkZjBMBggr
BgEFBQcCAjBAHj4AQwBlAHIAdABpAGYAaQBjAGEAZABvACAAcABhAHIAYQAgAHUA
cwBvACAAVAByAGkAYgB1AHQAYQByAGkAbzCB6AYDVR0fBIHgMIHdMIHaoIHXoIHU
hoHRaHR0cDovL2NhZmlybWEuaWRvay5jbC9lamJjYS9wdWJsaWN3ZWIvd2ViZGlz
dC9jZXJ0ZGlzdD9jbWQ9Y3JsJmlzc3Vlcj1FPXNvcG9ydGVAaWRvay5jbCxDTj1J
RE9LJTIwRklSTUElMjBFTEVDVFJPTklDQSUyMFY0LE9VPVJVVC03NjYxMDcxOC00
LE9VPUF1dG9yaWRhZCUyMENlcnRpZmljYWRvcmEsTz1CUE8lMjBBZHZpc29ycyUy
MFNwQSxMPVNhbnRpYWdvLEM9Q0wwHQYDVR0OBBYEFM8ChD5cUEwBw2zeGGYrVwbg
5zHFMAsGA1UdDwQEAwIEkDAjBgNVHRIEHDAaoBgGCCsGAQQBwQECoAwWCjc2NjEw
NzE4LTQwIwYDVR0RBBwwGqAYBggrBgEEAcEBAaAMFgowOTY2OTk5Ni00MA0GCSqG
SIb3DQEBCwUAA4IBAQBk/F87fYE7lediV9yTXFXWD66XeTYtKgJtRkzORVjcdTdt
MF0md0A290zteF2uD4JXdXr45Bw/Ul7ClHagr4EAG+lr+nyIwL+61bINK/E8zpia
wknPnJy61WvFLxHU5Yk1WetTrJzw8R2A+rLof7WBOiSNKaqYPSqbJew7UXb/uT9+
gXdMu9AUZxJDXsRYhibkKNAecPXaOWwYjEWm7QtOq9aOsx3oLkjxBFzR612xhn2n
YcuXXRabil0b8r6xwJ6UNOeKrugzuoylt+QXfUBsR0SNq/qHVQyTw1uq4n09N4Zu
nqRCOl3OLewGSqas9XlREFTrRsF0Nvsh0k1yyukd</X509Certificate></X509Data></KeyInfo></Signature></DTE>
    </SetDTE>

<Signature xmlns="http://www.w3.org/2000/09/xmldsig#"><SignedInfo xmlns="http://www.w3.org/2000/09/xmldsig#" xmlns:xsi="http://www.w3.org/2001/XMLSchema-instance"><CanonicalizationMethod Algorithm="http://www.w3.org/TR/2001/REC-xml-c14n-20010315"></CanonicalizationMethod><SignatureMethod Algorithm="http://www.w3.org/2000/09/xmldsig#rsa-sha1"></SignatureMethod><Reference URI="#SetDoc"><Transforms><Transform Algorithm="http://www.w3.org/TR/2001/REC-xml-c14n-20010315"></Transform></Transforms><DigestMethod Algorithm="http://www.w3.org/2000/09/xmldsig#sha1"></DigestMethod><DigestValue>QVXhQm8eq1TIN2DeC9zuaioW9NA=</DigestValue></Reference></SignedInfo><SignatureValue>AUC1XseiJ0QsnSacQBdnctGJhEab90sZ3L0UCSqcFaEjrK8R/AtIKv7LorPTr00kkajZ7Av62ZbklAbRi/Uf8xmE9cze/FlqjDzCCStQdRD2X39lD04Dxc4lWG4NYybxnvtrXVOU70nOC7wj3YgmbKAGYkHVu4OYYHeyWxG459aTYXMgutL26MzVfsXCm+2KUGQ1hGcUMneTPn7VTb3JeRh2zogiwSju0TzRsbt9Maoijyvb7vyF3yi/5BHSzt5UXUOe5NljmykfHUrAISDIle9ioNafvDDJDKWkD2VDqO3+ohZ2IwZlolPm92EjeLN7Iuj2LVaa9PfyIUzzDMy4+g==</SignatureValue><KeyInfo><KeyValue><RSAKeyValue><Modulus>zB803gl7VOefQ+HBWUfQ8yxV0rd+wPI/PSSUXNxk8OrhoulkxGA2t0EJXMdl1WjBuOHiDqI0ba4xRZ2BPBq0h3+he4O3wMBegfdTUsQ60l0VzGI3QxaeVfroU81gDZU+LI5m5Y8HgNnije2Oggn7dWB56Jidw5ybwTNT5/28fben2ot4RDcgJYRdTZO/T2Is5A3imjiqPRXRFFzhuiB2GxyKN3ABzu5+kwfZIXtzbrJzm3pZ1SAHtgHo+nf4sA0sAZ+rP55jGt8xOcNlVs5epLfleC1gyHna4j0sNQDEm2sc8rzWm4nqCHfB1yXlke4THH1urzUZ7DhTDui+qZIR+Q==</Modulus><Exponent>AQAB</Exponent></RSAKeyValue></KeyValue><X509Data><X509Certificate>
MIIF6jCCBNKgAwIBAgIICDFeKOa8KIIwDQYJKoZIhvcNAQELBQAwgboxHjAcBgkq
hkiG9w0BCQEWD3NvcG9ydGVAaWRvay5jbDEiMCAGA1UEAwwZSURPSyBGSVJNQSBF
TEVDVFJPTklDQSBWNDEXMBUGA1UECwwOUlVULTc2NjEwNzE4LTQxIDAeBgNVBAsM
F0F1dG9yaWRhZCBDZXJ0aWZpY2Fkb3JhMRkwFwYDVQQKDBBCUE8gQWR2aXNvcnMg
U3BBMREwDwYDVQQHDAhTYW50aWFnbzELMAkGA1UEBhMCQ0wwHhcNMjQxMjA2MTgy
NzU4WhcNMjUxMjA2MTgyNzU4WjB/MScwJQYDVQQDDB5TQU5EUkEgIEtBVElBIENB
TFZPIEJVU1RBTUFOVEUxJjAkBgkqhkiG9w0BCQEWF2NvbnRhYmlsaWRhZEBhZGFw
dG9yLmNsMRIwEAYDVQQFEwk5NjY5OTk2LTQxCzAJBgNVBAYTAkNMMQswCQYDVQQH
DAJSTTCCASIwDQYJKoZIhvcNAQEBBQADggEPADCCAQoCggEBAMwfNN4Je1Tnn0Ph
wVlH0PMsVdK3fsDyPz0klFzcZPDq4aLpZMRgNrdBCVzHZdVowbjh4g6iNG2uMUWd
gTwatId/oXuDt8DAXoH3U1LEOtJdFcxiN0MWnlX66FPNYA2VPiyOZuWPB4DZ4o3t
joIJ+3VgeeiYncOcm8EzU+f9vH23p9qLeEQ3ICWEXU2Tv09iLOQN4po4qj0V0RRc
4bogdhscijdwAc7ufpMH2SF7c26yc5t6WdUgB7YB6Pp3+LANLAGfqz+eYxrfMTnD
ZVbOXqS35XgtYMh52uI9LDUAxJtrHPK81puJ6gh3wdcl5ZHuExx9bq81Gew4Uw7o
vqmSEfkCAwEAAaOCAiwwggIoMAkGA1UdEwQCMAAwHwYDVR0jBBgwFoAUu91K238Q
N4h0Z0WyyrkShODGeBYwgZgGA1UdIASBkDCBjTCBigYKKwYBBAGDjB4BBDB8MCwG
CCsGAQUFBwIBFiBodHRwczovL3BzYy5pZG9rLmNsL29wZW4vY3BzLnBkZjBMBggr
BgEFBQcCAjBAHj4AQwBlAHIAdABpAGYAaQBjAGEAZABvACAAcABhAHIAYQAgAHUA
cwBvACAAVAByAGkAYgB1AHQAYQByAGkAbzCB6AYDVR0fBIHgMIHdMIHaoIHXoIHU
hoHRaHR0cDovL2NhZmlybWEuaWRvay5jbC9lamJjYS9wdWJsaWN3ZWIvd2ViZGlz
dC9jZXJ0ZGlzdD9jbWQ9Y3JsJmlzc3Vlcj1FPXNvcG9ydGVAaWRvay5jbCxDTj1J
RE9LJTIwRklSTUElMjBFTEVDVFJPTklDQSUyMFY0LE9VPVJVVC03NjYxMDcxOC00
LE9VPUF1dG9yaWRhZCUyMENlcnRpZmljYWRvcmEsTz1CUE8lMjBBZHZpc29ycyUy
MFNwQSxMPVNhbnRpYWdvLEM9Q0wwHQYDVR0OBBYEFM8ChD5cUEwBw2zeGGYrVwbg
5zHFMAsGA1UdDwQEAwIEkDAjBgNVHRIEHDAaoBgGCCsGAQQBwQECoAwWCjc2NjEw
NzE4LTQwIwYDVR0RBBwwGqAYBggrBgEEAcEBAaAMFgowOTY2OTk5Ni00MA0GCSqG
SIb3DQEBCwUAA4IBAQBk/F87fYE7lediV9yTXFXWD66XeTYtKgJtRkzORVjcdTdt
MF0md0A290zteF2uD4JXdXr45Bw/Ul7ClHagr4EAG+lr+nyIwL+61bINK/E8zpia
wknPnJy61WvFLxHU5Yk1WetTrJzw8R2A+rLof7WBOiSNKaqYPSqbJew7UXb/uT9+
gXdMu9AUZxJDXsRYhibkKNAecPXaOWwYjEWm7QtOq9aOsx3oLkjxBFzR612xhn2n
YcuXXRabil0b8r6xwJ6UNOeKrugzuoylt+QXfUBsR0SNq/qHVQyTw1uq4n09N4Zu
nqRCOl3OLewGSqas9XlREFTrRsF0Nvsh0k1yyukd</X509Certificate></X509Data></KeyInfo></Signature></EnvioDTE>